Winkit/__init__.py
Winsdoc/__init__.py
Winsdoc/__main__.py
Winstree/__init__.py
Winstree/DotNet/__init__.py
Winstree/DotNet/System/__init__.py
Winstree/DotNet/System/Drawing/__init__.py
Winstree/DotNet/System/Threading/__init__.py
Winstree/DotNet/System/Windows/__init__.py
Winstree/DotNet/System/Windows/Forms/__init__.py
Winstreer/__init__.py
Winstree-0.0.1a4.dist-info/METADATA
Winstree-0.0.1a4.dist-info/WHEEL
Winstree-0.0.1a4.dist-info/entry_points.txt
Winstree-0.0.1a4.dist-info/top_level.txt
Winstree-0.0.1a4.dist-info/RECORD
