Metadata-Version: 2.1
Name: Winstree
Version: 0.0.1a4
Summary: Windows环境.NET快速开发工具包
Author: XiangQinxi
Author-email: XiangQinxi@outlook.com
Classifier: Programming Language :: Python :: 3
Classifier: License :: OSI Approved :: MIT License
Classifier: Operating System :: OS Independent
Requires-Python: >=3.6
Requires-Dist: pythonnet (>=3.0.0a1)
